{
    "response": [
        {
            "maintainer": "mirukurusan",
            "oem": "LGE",
            "device": "LG G7 ThinQ",
            "filename": "crDroidAndroid-16.0-20251209-judyln-v12.4.zip",
            "download": "https://github.com/mirukurusan/rom_build/releases/download/crDroidAndroid-16.0-20251209-judyln-v12.4/crDroidAndroid-16.0-20251209-judyln-v12.4.zip",
            "timestamp": 1765258588,
            "md5": "bd3af331bd8cab5082892524ebaeff2f",
            "sha256": "6ca01d6a5032a0c8865dc80f43bd3181ba5349a5cd72376961b0e47a046bcfcc",
            "size": 1180548345,
            "version": "12.4",
            "buildtype": "Monthly",
            "forum": "https://xdaforums.com/c/lg-g7-thinq.7670/",
            "gapps": "https://sourceforge.net/projects/nikgapps/files/Elite-Releases/crdroid-official/Android-16/28-Nov-2025/NikGapps-crdroid-official-arm64-16-20251128-signed.zip/download",
            "firmware": "",
            "modem": "",
            "bootloader": "",
            "recovery": "",
            "paypal": "",
            "telegram": "",
            "dt": "",
            "common-dt": "",
            "kernel": ""
        }
    ]
}
